create_python_cmd/__init__.py
create_python_cmd/cli.py
create_python_cmd/createapp.py
create_python_cmd-2.0.2.dist-info/licenses/LICENSE
create_python_cmd-2.0.2.dist-info/METADATA
create_python_cmd-2.0.2.dist-info/WHEEL
create_python_cmd-2.0.2.dist-info/entry_points.txt
create_python_cmd-2.0.2.dist-info/top_level.txt
create_python_cmd-2.0.2.dist-info/RECORD
