Metadata-Version: 2.4
Name: create-python-cmd
Version: 2.0.2
Summary: Cross platform(ish) productivity commands written in python.
Home-page: https://github.com/zackees/create-python-cmd
Author: Zachary Vorhies
Maintainer: Zachary Vorhies
License: BSD 3-Clause License
Keywords: create python cmd
Classifier: Programming Language :: Python :: 3
Requires-Python: >=3.8
License-File: LICENSE
Requires-Dist: ruff
Requires-Dist: pyright
Requires-Dist: black
Requires-Dist: pytest
Requires-Dist: pytest-xdist
Requires-Dist: pytest-timeout
Requires-Dist: pytest-cov
Dynamic: author
Dynamic: home-page
Dynamic: license-file
Dynamic: maintainer
